mlf_api/__init__.py
mlf_api/inverse_kinematics.py
mlf_api/robot.py
mlf_api/signaling.py
mlf_api/videoShow.py
mlf_api/webRTC.py
mlf_api-0.2.7.dist-info/licenses/LICENSE
mlf_api-0.2.7.dist-info/METADATA
mlf_api-0.2.7.dist-info/WHEEL
mlf_api-0.2.7.dist-info/top_level.txt
mlf_api-0.2.7.dist-info/RECORD
