Metadata-Version: 2.4
Name: mlf-api
Version: 0.2.7
License-File: LICENSE
Requires-Dist: aiohttp==3.8.4
Requires-Dist: aiortc
Requires-Dist: numpy==1.24.3
Requires-Dist: opencv-python==4.7.0.72
Requires-Dist: requests==2.31.0
Dynamic: license-file
Dynamic: requires-dist
